app/__init__.py
app/girow.py
girow-0.0.1.dist-info/LICENSE
girow-0.0.1.dist-info/METADATA
girow-0.0.1.dist-info/WHEEL
girow-0.0.1.dist-info/entry_points.txt
girow-0.0.1.dist-info/top_level.txt
girow-0.0.1.dist-info/RECORD
